wqdab/__init__.py
wqdab/data.py
wqdab/metrics.py
wqdab/utils.py
wqdab-0.0.6.dist-info/LICENSE
wqdab-0.0.6.dist-info/METADATA
wqdab-0.0.6.dist-info/WHEEL
wqdab-0.0.6.dist-info/top_level.txt
wqdab-0.0.6.dist-info/RECORD
